LICENSE
README.md
setup.cfg
setup.py
easy_generate_excel/__init__.py
easy_generate_excel/sheet.py
easy_generate_excel/workbook.py
easy_generate_excel.egg-info/PKG-INFO
easy_generate_excel.egg-info/SOURCES.txt
easy_generate_excel.egg-info/dependency_links.txt
easy_generate_excel.egg-info/requires.txt
easy_generate_excel.egg-info/top_level.txt