Metadata-Version: 2.1
Name: easy-generate-excel
Version: 0.0.5
Summary: Easy generate excel files
Home-page: https://github.com/y0gurt-dv/Easy-generate-excel
Author: Daniil y0gur-dv
License: UNKNOWN
Keywords: excel,generators,easy
Platform: UNKNOWN
License-File: LICENSE
